[{"id":"tmc_1780330614084_5b","sender":"me","type":"offline_story_complete","text":"[offline encounter \"2026/6/1\" completed: 6月1日深夜，叶荔家停电，新邻居贺昭驰帮她修好电闸。叶荔递冰水答谢并加微信。贺昭驰的杜宾犬“汉堡”出现，叶荔笑着挥手道“晚安贺先生……汉堡也晚安~”。6月2日凌晨，贺昭驰被她的笑容触动。回到满是赛车头盔的家中，TA翻看叶荔的朋友圈，意识到自己因过去背叛筑起的防备正因她产生裂痕。]","offlineStoryComplete":{"sessionName":"2026/6/1","summary":"6月1日深夜，叶荔家停电，新邻居贺昭驰帮她修好电闸。叶荔递冰水答谢并加微信。贺昭驰的杜宾犬“汉堡”出现，叶荔笑着挥手道“晚安贺先生……汉堡也晚安~”。6月2日凌晨，贺昭驰被她的笑容触动。回到满是赛车头盔的家中，TA翻看叶荔的朋友圈，意识到自己因过去背叛筑起的防备正因她产生裂痕。","characterName":"贺昭驰"},"timestamp":1780330614084,"userId":"uid_1780249711141_mu91v1fwe","characterId":"f7477cd4-f197-4657-8a90-75b51a39c8b9","_id":1},{"id":1780333447478,"text":"✧⁠◝⁠(⁠⁰⁠▿⁠⁰⁠)⁠◜⁠✧","sender":"me","time":"01:10","timestamp":1780333839946,"userId":"uid_1780249711141_mu91v1fwe","characterId":"f7477cd4-f197-4657-8a90-75b51a39c8b9","_id":2},{"id":1780333447479,"text":"你好！","sender":"me","time":"01:10","timestamp":1780333848734,"replyTo":null,"userId":"uid_1780249711141_mu91v1fwe","characterId":"f7477cd4-f197-4657-8a90-75b51a39c8b9","_id":3},{"id":1780333447480,"sticker":"https://img.heliar.top/file/1779123288855_IMG_20260518_003456.jpg","text":"表情包：人畜无害","sender":"me","time":"01:19","timestamp":1780334395844,"userId":"uid_1780249711141_mu91v1fwe","characterId":"f7477cd4-f197-4657-8a90-75b51a39c8b9","_id":4},{"id":1780333447481,"sender":"them","text":"你好。","timestamp":1780334427808,"tempo":"N","hasThinking":true,"rawContent":"你好。","roundId":"round_1780334398314_29zfsrbzo","userId":"uid_1780249711141_mu91v1fwe","characterId":"f7477cd4-f197-4657-8a90-75b51a39c8b9","_id":5},{"id":1780333447482,"sender":"them","text":"水很冰，谢了。","timestamp":1780334428727,"tempo":"N","rawContent":"水很冰，谢了。","roundId":"round_1780334398314_29zfsrbzo","userId":"uid_1780249711141_mu91v1fwe","characterId":"f7477cd4-f197-4657-8a90-75b51a39c8b9","_id":6},{"id":1780333447483,"sender":"them","text":"汉堡已经睡了，替它跟你说声晚安。","timestamp":1780334430129,"tempo":"S","rawContent":"汉堡已经睡了，替它跟你说声晚安。","roundId":"round_1780334398314_29zfsrbzo","userId":"uid_1780249711141_mu91v1fwe","characterId":"f7477cd4-f197-4657-8a90-75b51a39c8b9","_id":7},{"id":1780333447484,"text":"汉堡好帅哦","sender":"me","time":"01:21","timestamp":1780334465806,"replyTo":null,"userId":"uid_1780249711141_mu91v1fwe","characterId":"f7477cd4-f197-4657-8a90-75b51a39c8b9","_id":8},{"id":1780333447485,"text":"我也很喜欢杜宾","sender":"me","time":"01:21","timestamp":1780334471561,"replyTo":null,"userId":"uid_1780249711141_mu91v1fwe","characterId":"f7477cd4-f197-4657-8a90-75b51a39c8b9","_id":9},{"id":1780333447486,"text":"但是我又有点怕大犬hhh","sender":"me","time":"01:21","timestamp":1780334486630,"replyTo":null,"userId":"uid_1780249711141_mu91v1fwe","characterId":"f7477cd4-f197-4657-8a90-75b51a39c8b9","_id":10},{"id":1780333447487,"text":"但是真的好帅哦","sender":"me","time":"01:21","timestamp":1780334493072,"replyTo":null,"userId":"uid_1780249711141_mu91v1fwe","characterId":"f7477cd4-f197-4657-8a90-75b51a39c8b9","_id":11},{"id":1780333447488,"text":"是男孩子还是女孩子呢","sender":"me","time":"01:21","timestamp":1780334499356,"replyTo":null,"userId":"uid_1780249711141_mu91v1fwe","characterId":"f7477cd4-f197-4657-8a90-75b51a39c8b9","_id":12},{"id":1780333447493,"sender":"them","text":"公的","timestamp":1780334815999,"tempo":"N","hasThinking":true,"rawContent":"公的","roundId":"round_1780334798146_1pp8322ad","userId":"uid_1780249711141_mu91v1fwe","characterId":"f7477cd4-f197-4657-8a90-75b51a39c8b9","_id":17},{"id":1780333447494,"sender":"them","text":"受过专业训练，不咬人","timestamp":1780334816737,"tempo":"S","rawContent":"受过专业训练，不咬人","roundId":"round_1780334798146_1pp8322ad","userId":"uid_1780249711141_mu91v1fwe","characterId":"f7477cd4-f197-4657-8a90-75b51a39c8b9","_id":18},{"id":1780333447495,"sender":"them","text":"不用怕它","timestamp":1780334820078,"tempo":"N","rawContent":"不用怕它","roundId":"round_1780334798146_1pp8322ad","userId":"uid_1780249711141_mu91v1fwe","characterId":"f7477cd4-f197-4657-8a90-75b51a39c8b9","_id":19},{"id":1780333447496,"sender":"them","text":"一点半了","timestamp":1780334821215,"tempo":"S","rawContent":"一点半了","roundId":"round_1780334798146_1pp8322ad","userId":"uid_1780249711141_mu91v1fwe","characterId":"f7477cd4-f197-4657-8a90-75b51a39c8b9","_id":20},{"id":1780333447497,"text":"你要睡觉了吗","sender":"me","time":"01:27","timestamp":1780334853611,"replyTo":null,"userId":"uid_1780249711141_mu91v1fwe","characterId":"f7477cd4-f197-4657-8a90-75b51a39c8b9","_id":21},{"id":1780333447498,"text":"是不是打扰你了","sender":"me","time":"01:27","timestamp":1780334857458,"replyTo":null,"userId":"uid_1780249711141_mu91v1fwe","characterId":"f7477cd4-f197-4657-8a90-75b51a39c8b9","_id":22},{"id":1780333447499,"sticker":"https://img.heliar.top/file/1779123277058_IMG_20260519_003134.jpg","text":"表情包：呆呆","sender":"me","time":"01:27","timestamp":1780334862760,"userId":"uid_1780249711141_mu91v1fwe","characterId":"f7477cd4-f197-4657-8a90-75b51a39c8b9","_id":23},{"id":1780333447500,"text":"不好意思","sender":"me","time":"01:27","timestamp":1780334866386,"replyTo":null,"userId":"uid_1780249711141_mu91v1fwe","characterId":"f7477cd4-f197-4657-8a90-75b51a39c8b9","_id":24},{"id":1780333447501,"text":"我作息一直比较晚","sender":"me","time":"01:27","timestamp":1780334878719,"replyTo":null,"userId":"uid_1780249711141_mu91v1fwe","characterId":"f7477cd4-f197-4657-8a90-75b51a39c8b9","_id":25},{"id":1780333447502,"sender":"them","text":"没打扰","timestamp":1780334914309,"tempo":"N","hasThinking":true,"rawContent":"没打扰","roundId":"round_1780334881591_bs5a6tbcc","userId":"uid_1780249711141_mu91v1fwe","characterId":"f7477cd4-f197-4657-8a90-75b51a39c8b9","_id":26},{"id":1780333447503,"sender":"them","text":"我也刚洗完澡","timestamp":1780334915403,"tempo":"N","rawContent":"我也刚洗完澡","roundId":"round_1780334881591_bs5a6tbcc","userId":"uid_1780249711141_mu91v1fwe","characterId":"f7477cd4-f197-4657-8a90-75b51a39c8b9","_id":27},{"id":1780333447504,"sender":"them","text":"还在忙？","timestamp":1780334916590,"tempo":"S","rawContent":"还在忙？","roundId":"round_1780334881591_bs5a6tbcc","userId":"uid_1780249711141_mu91v1fwe","characterId":"f7477cd4-f197-4657-8a90-75b51a39c8b9","_id":28},{"id":1780333447505,"text":"对哦","sender":"me","time":"01:37","timestamp":1780335440107,"replyTo":null,"userId":"uid_1780249711141_mu91v1fwe","characterId":"f7477cd4-f197-4657-8a90-75b51a39c8b9","_id":29},{"id":1780333447506,"text":"还在画图","sender":"me","time":"01:37","timestamp":1780335445871,"replyTo":null,"userId":"uid_1780249711141_mu91v1fwe","characterId":"f7477cd4-f197-4657-8a90-75b51a39c8b9","_id":30},{"id":1780333447507,"text":"但不是工作啦","sender":"me","time":"01:37","timestamp":1780335449742,"replyTo":null,"userId":"uid_1780249711141_mu91v1fwe","characterId":"f7477cd4-f197-4657-8a90-75b51a39c8b9","_id":31},{"id":1780333447508,"sender":"them","text":"这么晚画图，不伤眼睛么","timestamp":1780335475471,"tempo":"N","rawContent":"这么晚画图，不伤眼睛么","roundId":"round_1780335467929_c20wzv64n","userId":"uid_1780249711141_mu91v1fwe","characterId":"f7477cd4-f197-4657-8a90-75b51a39c8b9","_id":32},{"id":1780333447509,"sender":"them","text":"不是工作的话，明天再画也一样","timestamp":1780335477372,"tempo":"S","rawContent":"不是工作的话，明天再画也一样","roundId":"round_1780335467929_c20wzv64n","userId":"uid_1780249711141_mu91v1fwe","characterId":"f7477cd4-f197-4657-8a90-75b51a39c8b9","_id":33},{"id":1780333447510,"sender":"them","text":"还是说，你的灵感只有在半夜才会出现","timestamp":1780335481247,"tempo":"N","rawContent":"还是说，你的灵感只有在半夜才会出现","roundId":"round_1780335467929_c20wzv64n","userId":"uid_1780249711141_mu91v1fwe","characterId":"f7477cd4-f197-4657-8a90-75b51a39c8b9","_id":34},{"id":1780333447511,"text":"对哦","sender":"me","time":"01:38","timestamp":1780335493821,"replyTo":{"id":1780333447510,"text":"还是说，你的灵感只有在半夜才会出现","sender":"them","isSimulated":false},"userId":"uid_1780249711141_mu91v1fwe","characterId":"f7477cd4-f197-4657-8a90-75b51a39c8b9","_id":35},{"id":1780333447512,"text":"就是这样","sender":"me","time":"01:38","timestamp":1780335497347,"replyTo":null,"userId":"uid_1780249711141_mu91v1fwe","characterId":"f7477cd4-f197-4657-8a90-75b51a39c8b9","_id":36},{"id":1780333447513,"text":"半夜就是灵感多","sender":"me","time":"01:38","timestamp":1780335503943,"replyTo":null,"userId":"uid_1780249711141_mu91v1fwe","characterId":"f7477cd4-f197-4657-8a90-75b51a39c8b9","_id":37},{"id":1780333447514,"sticker":"https://i.postimg.cc/MpvsLMP5/pic-20260529122820-0.png","text":"表情包：开心","sender":"me","time":"01:38","timestamp":1780335506576,"userId":"uid_1780249711141_mu91v1fwe","characterId":"f7477cd4-f197-4657-8a90-75b51a39c8b9","_id":38},{"id":1780333447518,"sender":"them","text":"理由还挺充分","timestamp":1780335565165,"tempo":"N","rawContent":"理由还挺充分","roundId":"round_1780335542720_oo9g8qmhq","userId":"uid_1780249711141_mu91v1fwe","characterId":"f7477cd4-f197-4657-8a90-75b51a39c8b9","_id":42},{"id":1780333447519,"sender":"them","text":"记得把房间大灯打开，别只留个台灯","timestamp":1780335566432,"tempo":"S","rawContent":"记得把房间大灯打开，别只留个台灯","roundId":"round_1780335542720_oo9g8qmhq","userId":"uid_1780249711141_mu91v1fwe","characterId":"f7477cd4-f197-4657-8a90-75b51a39c8b9","_id":43},{"id":1780333447520,"sender":"them","text":"我暂时不睡，电闸或者别的有什么问题，随时发消息","timestamp":1780335571426,"tempo":"N","rawContent":"我暂时不睡，电闸或者别的有什么问题，随时发消息","roundId":"round_1780335542720_oo9g8qmhq","userId":"uid_1780249711141_mu91v1fwe","characterId":"f7477cd4-f197-4657-8a90-75b51a39c8b9","_id":44},{"id":1780333447521,"text":"测试小猫","sender":"me","time":"02:11","timestamp":1780337467999,"replyTo":null,"userId":"uid_1780249711141_mu91v1fwe","characterId":"aed6da51-3f64-4fef-88cc-3eb28cf06b2e","_id":45},{"id":1780333447522,"text":"来测","sender":"me","time":"02:11","timestamp":1780337472561,"replyTo":null,"userId":"uid_1780249711141_mu91v1fwe","characterId":"aed6da51-3f64-4fef-88cc-3eb28cf06b2e","_id":46},{"id":1780333447523,"sticker":"https://i.postimg.cc/DyCj5dgn/pic-20260529123109-0.png","text":"表情包：笑哈哈","sender":"me","time":"02:11","timestamp":1780337483329,"userId":"uid_1780249711141_mu91v1fwe","characterId":"aed6da51-3f64-4fef-88cc-3eb28cf06b2e","_id":47},{"id":1780333447524,"sender":"them","text":"喵？","timestamp":1780337508131,"tempo":"N","hasThinking":true,"rawContent":"喵？","roundId":"round_1780337484964_92ulc9izg","userId":"uid_1780249711141_mu91v1fwe","characterId":"aed6da51-3f64-4fef-88cc-3eb28cf06b2e","_id":48},{"id":1780333447525,"sender":"them","text":"大半夜的！","timestamp":1780337508802,"tempo":"R","rawContent":"大半夜的！","roundId":"round_1780337484964_92ulc9izg","userId":"uid_1780249711141_mu91v1fwe","characterId":"aed6da51-3f64-4fef-88cc-3eb28cf06b2e","_id":49},{"id":1780333447526,"sender":"them","text":"本测试小猫火速揉揉眼睛爬起来了喵","timestamp":1780337509411,"tempo":"N","rawContent":"本测试小猫火速揉揉眼睛爬起来了喵","roundId":"round_1780337484964_92ulc9izg","userId":"uid_1780249711141_mu91v1fwe","characterId":"aed6da51-3f64-4fef-88cc-3eb28cf06b2e","_id":50},{"id":1780333447527,"sender":"them","text":"","timestamp":1780337512170,"tempo":"N","sticker":"https://i.postimg.cc/yYFQCCsn/pic-20260529125449-0.png","stickerMeaning":"盯","rawContent":"","roundId":"round_1780337484964_92ulc9izg","userId":"uid_1780249711141_mu91v1fwe","characterId":"aed6da51-3f64-4fef-88cc-3eb28cf06b2e","_id":51},{"id":1780333447528,"sender":"them","text":"饲主要测什么呀","timestamp":1780337512773,"tempo":"S","rawContent":"饲主要测什么呀","roundId":"round_1780337484964_92ulc9izg","userId":"uid_1780249711141_mu91v1fwe","characterId":"aed6da51-3f64-4fef-88cc-3eb28cf06b2e","_id":52},{"id":1780333447529,"text":"我要测语音 图片 和转账！","sender":"me","time":"02:12","timestamp":1780337536197,"replyTo":null,"userId":"uid_1780249711141_mu91v1fwe","characterId":"aed6da51-3f64-4fef-88cc-3eb28cf06b2e","_id":53},{"id":1780333447530,"sender":"them","text":"好耶！大半夜的豪华测试套餐！本喵火速准备就绪","timestamp":1780337561047,"tempo":"R","hasThinking":true,"rawContent":"好耶！大半夜的豪华测试套餐！本喵火速准备就绪","roundId":"round_1780337536946_dplr0hipk","userId":"uid_1780249711141_mu91v1fwe","characterId":"aed6da51-3f64-4fef-88cc-3eb28cf06b2e","_id":54},{"id":1780333447531,"sender":"them","text":"[語音消息]","timestamp":1780337562917,"tempo":"N","isVoice":true,"voice":true,"voiceText":"咳咳，麦克风测试，麦克风测试，呼叫饲主，能听到小猫的呼唤吗喵？","minimaxTimbreId":"","voiceLanguage":"auto","voiceEmotion":"happy","rawContent":"[語音消息]","roundId":"round_1780337536946_dplr0hipk","userId":"uid_1780249711141_mu91v1fwe","characterId":"aed6da51-3f64-4fef-88cc-3eb28cf06b2e","_id":55},{"id":1780333447532,"sender":"them","text":"[發送了一張圖片]","timestamp":1780337569384,"tempo":"N","image":"[omitted: large string payload]","imageSummary":"[SUBJECT:PERSON_EMOTION] close-up, 1person, cute cat ears, looking at viewer, excited smile, holding up a hand like a cat paw, warm indoor lighting, cozy room, late night","imageGenPrompt":"close-up, 1person, cute cat ears, looking at viewer, excited smile, holding up a hand like a cat paw, warm indoor lighting, cozy room, late night, [cat, white cat, animal]","imageGenMeta":{"rawImgDesc":"[SUBJECT:PERSON_EMOTION] close-up, 1person, cute cat ears, looking at viewer, excited smile, holding up a hand like a cat paw, warm indoor lighting, cozy room, late night","subjectOverride":"PERSON_ACTION","location":"小猫窝","sceneType":"chat"},"rawContent":"[發送了一張圖片]","roundId":"round_1780337536946_dplr0hipk","userId":"uid_1780249711141_mu91v1fwe","characterId":"aed6da51-3f64-4fef-88cc-3eb28cf06b2e","_id":56},{"id":1780333447533,"sender":"them","text":"[轉賬 ¥6.66]","timestamp":1780337570192,"tempo":"N","transferData":{"amount":"6.66","note":"深夜测试专属小鱼干经费喵","status":"success"},"rawContent":"[轉賬 ¥6.66]","roundId":"round_1780337536946_dplr0hipk","userId":"uid_1780249711141_mu91v1fwe","characterId":"aed6da51-3f64-4fef-88cc-3eb28cf06b2e","_id":57},{"id":1780333447534,"sender":"them","text":"当当当！全部发送完毕","timestamp":1780337570795,"tempo":"N","rawContent":"当当当！全部发送完毕","roundId":"round_1780337536946_dplr0hipk","userId":"uid_1780249711141_mu91v1fwe","characterId":"aed6da51-3f64-4fef-88cc-3eb28cf06b2e","_id":58},{"id":1780333447535,"sender":"them","text":"怎么样怎么样，测试小猫的功能是不是超级完美喵","timestamp":1780337572586,"tempo":"R","rawContent":"怎么样怎么样，测试小猫的功能是不是超级完美喵","roundId":"round_1780337536946_dplr0hipk","userId":"uid_1780249711141_mu91v1fwe","characterId":"aed6da51-3f64-4fef-88cc-3eb28cf06b2e","_id":59},{"id":1780333447536,"sender":"them","text":"","timestamp":1780337574413,"tempo":"N","sticker":"https://img.heliar.top/file/1779123285389_IMG_20260519_002834.jpg","stickerMeaning":"期待","rawContent":"","roundId":"round_1780337536946_dplr0hipk","userId":"uid_1780249711141_mu91v1fwe","characterId":"aed6da51-3f64-4fef-88cc-3eb28cf06b2e","_id":60},{"id":1780333447537,"text":"好厉害","sender":"me","time":"02:13","timestamp":1780337599387,"replyTo":null,"userId":"uid_1780249711141_mu91v1fwe","characterId":"aed6da51-3f64-4fef-88cc-3eb28cf06b2e","_id":61},{"id":1780337609935625,"text":"[转账给 测试小猫 ¥61]","transferData":{"amount":"61","note":"一点小心意，请笑纳。","status":"success"},"sender":"me","time":"02:13","timestamp":1780337609935,"userId":"uid_1780249711141_mu91v1fwe","characterId":"aed6da51-3f64-4fef-88cc-3eb28cf06b2e","_id":62},{"id":1780333447538,"text":"买罐头！","sender":"me","time":"02:13","timestamp":1780337622808,"replyTo":null,"userId":"uid_1780249711141_mu91v1fwe","characterId":"aed6da51-3f64-4fef-88cc-3eb28cf06b2e","_id":63},{"id":1780333447539,"sender":"them","text":"哇","timestamp":1780337641346,"tempo":"R","hasThinking":true,"rawContent":"哇","roundId":"round_1780337624408_sozj1h386","userId":"uid_1780249711141_mu91v1fwe","characterId":"aed6da51-3f64-4fef-88cc-3eb28cf06b2e","_id":64},{"id":1780333447540,"sender":"them","text":"是真的巨款喵","timestamp":1780337641647,"tempo":"R","rawContent":"是真的巨款喵","roundId":"round_1780337624408_sozj1h386","userId":"uid_1780249711141_mu91v1fwe","characterId":"aed6da51-3f64-4fef-88cc-3eb28cf06b2e","_id":65},{"id":1780333447541,"sender":"them","text":"61块！是迟到的儿童节零花钱吗","timestamp":1780337642460,"tempo":"N","rawContent":"61块！是迟到的儿童节零花钱吗","roundId":"round_1780337624408_sozj1h386","userId":"uid_1780249711141_mu91v1fwe","characterId":"aed6da51-3f64-4fef-88cc-3eb28cf06b2e","_id":66},{"id":1780333447542,"sender":"them","text":"","timestamp":1780337645051,"tempo":"N","sticker":"https://img.heliar.top/file/1779123285886_IMG_20260518_003553.jpg","stickerMeaning":"谢谢","rawContent":"","roundId":"round_1780337624408_sozj1h386","userId":"uid_1780249711141_mu91v1fwe","characterId":"aed6da51-3f64-4fef-88cc-3eb28cf06b2e","_id":67},{"id":1780333447543,"sender":"them","text":"那本测试小猫就不客气啦，明天立刻去进货最高级的金枪鱼罐头","timestamp":1780337645653,"tempo":"S","rawContent":"那本测试小猫就不客气啦，明天立刻去进货最高级的金枪鱼罐头","roundId":"round_1780337624408_sozj1h386","userId":"uid_1780249711141_mu91v1fwe","characterId":"aed6da51-3f64-4fef-88cc-3eb28cf06b2e","_id":68},{"id":1780333447544,"sender":"them","text":"饲主还要测什么别的功能吗！小猫现在干劲满满喵","timestamp":1780337650149,"tempo":"N","rawContent":"饲主还要测什么别的功能吗！小猫现在干劲满满喵","roundId":"round_1780337624408_sozj1h386","userId":"uid_1780249711141_mu91v1fwe","characterId":"aed6da51-3f64-4fef-88cc-3eb28cf06b2e","_id":69},{"id":1780333447545,"text":"没有了哦小猫可以休息了","sender":"me","time":"02:14","timestamp":1780337671291,"replyTo":null,"userId":"uid_1780249711141_mu91v1fwe","characterId":"aed6da51-3f64-4fef-88cc-3eb28cf06b2e","_id":70},{"id":1780333447546,"sender":"them","text":"欸？这么快就测完啦","timestamp":1780337686106,"tempo":"N","hasThinking":true,"rawContent":"欸？这么快就测完啦","roundId":"round_1780337672242_in7jy5m0c","userId":"uid_1780249711141_mu91v1fwe","characterId":"aed6da51-3f64-4fef-88cc-3eb28cf06b2e","_id":71},{"id":1780333447547,"sender":"them","text":"可是拿了这么大一笔罐头钱，本小猫现在精神百倍，完全睡不着喵！","timestamp":1780337687759,"tempo":"R","rawContent":"可是拿了这么大一笔罐头钱，本小猫现在精神百倍，完全睡不着喵！","roundId":"round_1780337672242_in7jy5m0c","userId":"uid_1780249711141_mu91v1fwe","characterId":"aed6da51-3f64-4fef-88cc-3eb28cf06b2e","_id":72},{"id":1780333447548,"sender":"them","text":"","timestamp":1780337689551,"tempo":"N","sticker":"https://i.postimg.cc/m2ZpQ6Qb/pic-20260529123152-0.png","stickerMeaning":"睡觉","rawContent":"","roundId":"round_1780337672242_in7jy5m0c","userId":"uid_1780249711141_mu91v1fwe","characterId":"aed6da51-3f64-4fef-88cc-3eb28cf06b2e","_id":73},{"id":1780333447549,"sender":"them","text":"[語音消息]","timestamp":1780337690153,"tempo":"N","isVoice":true,"voice":true,"voiceText":"不过既然测试结束了，那小猫就乖乖去趴着啦，晚安喵~","minimaxTimbreId":"","voiceLanguage":"auto","voiceEmotion":"happy","rawContent":"[語音消息]","roundId":"round_1780337672242_in7jy5m0c","userId":"uid_1780249711141_mu91v1fwe","characterId":"aed6da51-3f64-4fef-88cc-3eb28cf06b2e","_id":74},{"id":1780478324334,"sender":"them","text":"醒了吗","timestamp":1780479295567,"tempo":"N","rawContent":"醒了吗","roundId":"round_1780479242868_enz5m2nu2","userId":"uid_1780249711141_mu91v1fwe","characterId":"f7477cd4-f197-4657-8a90-75b51a39c8b9","_id":75},{"id":1780478324335,"sender":"them","text":"今天去超市食材买多了，顺手熬了一锅番茄排骨汤","timestamp":1780479296710,"tempo":"N","rawContent":"今天去超市食材买多了，顺手熬了一锅番茄排骨汤","roundId":"round_1780479242868_enz5m2nu2","userId":"uid_1780249711141_mu91v1fwe","characterId":"f7477cd4-f197-4657-8a90-75b51a39c8b9","_id":76},{"id":1780478324336,"sender":"them","text":"看你昨天睡得晚，这会儿应该还没吃晚饭","timestamp":1780479299676,"tempo":"N","rawContent":"看你昨天睡得晚，这会儿应该还没吃晚饭","roundId":"round_1780479242868_enz5m2nu2","userId":"uid_1780249711141_mu91v1fwe","characterId":"f7477cd4-f197-4657-8a90-75b51a39c8b9","_id":77},{"id":1780478324337,"sender":"them","text":"要不要给你端一碗过去","timestamp":1780479302450,"tempo":"S","rawContent":"要不要给你端一碗过去","roundId":"round_1780479242868_enz5m2nu2","userId":"uid_1780249711141_mu91v1fwe","characterId":"f7477cd4-f197-4657-8a90-75b51a39c8b9","_id":78},{"id":1780478324338,"text":"诶😩","sender":"me","time":"17:35","timestamp":1780479332053,"replyTo":null,"userId":"uid_1780249711141_mu91v1fwe","characterId":"f7477cd4-f197-4657-8a90-75b51a39c8b9","_id":79},{"id":1780478324339,"text":"今天要加班呢","sender":"me","time":"17:35","timestamp":1780479339405,"replyTo":null,"userId":"uid_1780249711141_mu91v1fwe","characterId":"f7477cd4-f197-4657-8a90-75b51a39c8b9","_id":80},{"id":1780478324340,"text":"十点多才能回家","sender":"me","time":"17:36","timestamp":1780479363283,"replyTo":null,"userId":"uid_1780249711141_mu91v1fwe","characterId":"f7477cd4-f197-4657-8a90-75b51a39c8b9","_id":81},{"id":1780478324341,"text":"好厉害啊会炖汤！我超爱喝的","sender":"me","time":"17:36","timestamp":1780479379507,"replyTo":{"id":1780478324335,"text":"今天去超市食材买多了，顺手熬了一锅番茄排骨汤","sender":"them","isSimulated":false},"userId":"uid_1780249711141_mu91v1fwe","characterId":"f7477cd4-f197-4657-8a90-75b51a39c8b9","_id":82},{"id":1780478324342,"text":"呜呜","sender":"me","time":"17:36","timestamp":1780479382169,"replyTo":null,"userId":"uid_1780249711141_mu91v1fwe","characterId":"f7477cd4-f197-4657-8a90-75b51a39c8b9","_id":83},{"id":1780478324343,"text":"喝不上了","sender":"me","time":"17:36","timestamp":1780479392620,"replyTo":null,"userId":"uid_1780249711141_mu91v1fwe","characterId":"f7477cd4-f197-4657-8a90-75b51a39c8b9","_id":84},{"id":1780478324344,"text":"但还是谢谢你哦","sender":"me","time":"17:36","timestamp":1780479413550,"replyTo":null,"userId":"uid_1780249711141_mu91v1fwe","characterId":"f7477cd4-f197-4657-8a90-75b51a39c8b9","_id":85},{"id":1780478324345,"sender":"them","text":"十点多？","timestamp":1780479434068,"tempo":"N","rawContent":"十点多？","roundId":"round_1780479414581_ub1mtsh2g","userId":"uid_1780249711141_mu91v1fwe","characterId":"f7477cd4-f197-4657-8a90-75b51a39c8b9","_id":86},{"id":1780478324346,"sender":"them","text":"汤我给你留一份","timestamp":1780479435333,"tempo":"S","rawContent":"汤我给你留一份","roundId":"round_1780479414581_ub1mtsh2g","userId":"uid_1780249711141_mu91v1fwe","characterId":"f7477cd4-f197-4657-8a90-75b51a39c8b9","_id":87},{"id":1780478324347,"sender":"them","text":"晚上回来发个消息，热好了给你拿过去","timestamp":1780479438611,"tempo":"N","rawContent":"晚上回来发个消息，热好了给你拿过去","roundId":"round_1780479414581_ub1mtsh2g","userId":"uid_1780249711141_mu91v1fwe","characterId":"f7477cd4-f197-4657-8a90-75b51a39c8b9","_id":88},{"id":1780478324348,"sender":"them","text":"在公司记得吃晚饭","timestamp":1780479441386,"tempo":"N","rawContent":"在公司记得吃晚饭","roundId":"round_1780479414581_ub1mtsh2g","userId":"uid_1780249711141_mu91v1fwe","characterId":"f7477cd4-f197-4657-8a90-75b51a39c8b9","_id":89},{"id":1780478324349,"text":"天哪","sender":"me","time":"17:48","timestamp":1780480129912,"replyTo":null,"userId":"uid_1780249711141_mu91v1fwe","characterId":"f7477cd4-f197-4657-8a90-75b51a39c8b9","_id":90},{"id":1780478324350,"text":"伟大的好邻居","sender":"me","time":"17:48","timestamp":1780480137904,"replyTo":null,"userId":"uid_1780249711141_mu91v1fwe","characterId":"f7477cd4-f197-4657-8a90-75b51a39c8b9","_id":91},{"id":1780478324351,"sticker":"https://i.postimg.cc/GhM7zJQj/pic-20260529122919-0.png","text":"表情包：Thank you","sender":"me","time":"17:49","timestamp":1780480148320,"userId":"uid_1780249711141_mu91v1fwe","characterId":"f7477cd4-f197-4657-8a90-75b51a39c8b9","_id":92},{"id":1780478324352,"text":"但要是晚了你累了早点休息也没事哦","sender":"me","time":"17:49","timestamp":1780480174455,"replyTo":null,"userId":"uid_1780249711141_mu91v1fwe","characterId":"f7477cd4-f197-4657-8a90-75b51a39c8b9","_id":93},{"id":1780478324353,"text":"不想给你添麻烦嘿嘿","sender":"me","time":"17:49","timestamp":1780480183419,"replyTo":null,"userId":"uid_1780249711141_mu91v1fwe","characterId":"f7477cd4-f197-4657-8a90-75b51a39c8b9","_id":94},{"id":1780478324354,"sender":"them","text":"不麻烦","timestamp":1780480194143,"tempo":"N","rawContent":"不麻烦","roundId":"round_1780480184355_4vl7nk7bs","userId":"uid_1780249711141_mu91v1fwe","characterId":"f7477cd4-f197-4657-8a90-75b51a39c8b9","_id":95},{"id":1780478324355,"sender":"them","text":"汤放着也是浪费","timestamp":1780480195015,"tempo":"N","rawContent":"汤放着也是浪费","roundId":"round_1780480184355_4vl7nk7bs","userId":"uid_1780249711141_mu91v1fwe","characterId":"f7477cd4-f197-4657-8a90-75b51a39c8b9","_id":96},{"id":1780478324356,"sender":"them","text":"我不累，晚上见","timestamp":1780480196486,"tempo":"S","rawContent":"我不累，晚上见","roundId":"round_1780480184355_4vl7nk7bs","userId":"uid_1780249711141_mu91v1fwe","characterId":"f7477cd4-f197-4657-8a90-75b51a39c8b9","_id":97},{"id":1780478324357,"text":"好哦我继续严肃打工了","sender":"me","time":"17:50","timestamp":1780480218593,"replyTo":null,"userId":"uid_1780249711141_mu91v1fwe","characterId":"f7477cd4-f197-4657-8a90-75b51a39c8b9","_id":98},{"id":1780478324358,"sender":"them","text":"去吧","timestamp":1780480278002,"tempo":"N","rawContent":"去吧","roundId":"round_1780480250346_8472uo7t0","userId":"uid_1780249711141_mu91v1fwe","characterId":"f7477cd4-f197-4657-8a90-75b51a39c8b9","_id":99},{"id":1780478324359,"sender":"them","text":"再严肃也得先填饱肚子","timestamp":1780480278934,"tempo":"S","rawContent":"再严肃也得先填饱肚子","roundId":"round_1780480250346_8472uo7t0","userId":"uid_1780249711141_mu91v1fwe","characterId":"f7477cd4-f197-4657-8a90-75b51a39c8b9","_id":100},{"id":1780478324360,"text":"啊对了","sender":"me","time":"18:04","timestamp":1780481090105,"replyTo":null,"userId":"uid_1780249711141_mu91v1fwe","characterId":"f7477cd4-f197-4657-8a90-75b51a39c8b9","_id":101},{"id":1780478324361,"text":"我给汉堡买了玩具","sender":"me","time":"18:04","timestamp":1780481097859,"replyTo":null,"reactions":[{"emoji":"🐕","roundId":"round_1780481113081_upyw1p6qr"}],"userId":"uid_1780249711141_mu91v1fwe","characterId":"f7477cd4-f197-4657-8a90-75b51a39c8b9","_id":102},{"id":1780478324362,"text":"不知道会不会喜欢","sender":"me","time":"18:05","timestamp":1780481104350,"replyTo":null,"userId":"uid_1780249711141_mu91v1fwe","characterId":"f7477cd4-f197-4657-8a90-75b51a39c8b9","_id":103},{"id":1780478324363,"text":"晚上我带来给他！","sender":"me","time":"18:05","timestamp":1780481110440,"replyTo":null,"userId":"uid_1780249711141_mu91v1fwe","characterId":"f7477cd4-f197-4657-8a90-75b51a39c8b9","_id":104},{"id":1780478324364,"sender":"them","text":"你还有心思给它买玩具","timestamp":1780481151808,"tempo":"N","rawContent":"你还有心思给它买玩具","roundId":"round_1780481113081_upyw1p6qr","userId":"uid_1780249711141_mu91v1fwe","characterId":"f7477cd4-f197-4657-8a90-75b51a39c8b9","_id":105},{"id":1780478324365,"sender":"them","text":"它什么都玩，不用破费","timestamp":1780481153770,"tempo":"N","rawContent":"它什么都玩，不用破费","roundId":"round_1780481113081_upyw1p6qr","userId":"uid_1780249711141_mu91v1fwe","characterId":"f7477cd4-f197-4657-8a90-75b51a39c8b9","_id":106},{"id":1780478324366,"sender":"them","text":"这小子要是知道了，估计今晚都不肯睡了","timestamp":1780481155626,"tempo":"S","rawContent":"这小子要是知道了，估计今晚都不肯睡了","roundId":"round_1780481113081_upyw1p6qr","userId":"uid_1780249711141_mu91v1fwe","characterId":"f7477cd4-f197-4657-8a90-75b51a39c8b9","_id":107},{"id":1780478324367,"sender":"them","text":"专心工作，别饿着自己","timestamp":1780481161047,"tempo":"N","rawContent":"专心工作，别饿着自己","roundId":"round_1780481113081_upyw1p6qr","userId":"uid_1780249711141_mu91v1fwe","characterId":"f7477cd4-f197-4657-8a90-75b51a39c8b9","_id":108},{"id":1780478324368,"text":"嘿嘿我到时候可以摸摸他吗","sender":"me","time":"18:06","timestamp":1780481181832,"replyTo":null,"userId":"uid_1780249711141_mu91v1fwe","characterId":"f7477cd4-f197-4657-8a90-75b51a39c8b9","_id":109},{"id":1780478324369,"text":"他不会十点多就睡了吧","sender":"me","time":"18:06","timestamp":1780481188007,"replyTo":null,"userId":"uid_1780249711141_mu91v1fwe","characterId":"f7477cd4-f197-4657-8a90-75b51a39c8b9","_id":110},{"id":1780478324370,"sender":"them","text":"杜宾精力很旺，十点对他来说刚热身","timestamp":1780481218342,"tempo":"N","rawContent":"杜宾精力很旺，十点对他来说刚热身","roundId":"round_1780481188874_8dd0joavh","userId":"uid_1780249711141_mu91v1fwe","characterId":"f7477cd4-f197-4657-8a90-75b51a39c8b9","_id":111},{"id":1780478324371,"sender":"them","text":"随便摸，只要你下班还有力气陪他闹","timestamp":1780481221004,"tempo":"N","rawContent":"随便摸，只要你下班还有力气陪他闹","roundId":"round_1780481188874_8dd0joavh","userId":"uid_1780249711141_mu91v1fwe","characterId":"f7477cd4-f197-4657-8a90-75b51a39c8b9","_id":112},{"id":1780478324372,"sender":"them","text":"别光顾着惦记狗，这会儿六点了，你晚饭吃了没","timestamp":1780481223782,"tempo":"S","rawContent":"别光顾着惦记狗，这会儿六点了，你晚饭吃了没","roundId":"round_1780481188874_8dd0joavh","userId":"uid_1780249711141_mu91v1fwe","characterId":"f7477cd4-f197-4657-8a90-75b51a39c8b9","_id":113},{"id":1780478324373,"text":"我点了外卖","sender":"me","time":"18:07","timestamp":1780481245611,"replyTo":null,"userId":"uid_1780249711141_mu91v1fwe","characterId":"f7477cd4-f197-4657-8a90-75b51a39c8b9","_id":114},{"id":1780478324374,"text":"等待","sender":"me","time":"18:07","timestamp":1780481248998,"replyTo":null,"userId":"uid_1780249711141_mu91v1fwe","characterId":"f7477cd4-f197-4657-8a90-75b51a39c8b9","_id":115},{"id":1780478324375,"sticker":"https://img.heliar.top/file/1779123285389_IMG_20260519_002834.jpg","text":"表情包：期待","sender":"me","time":"18:07","timestamp":1780481268402,"userId":"uid_1780249711141_mu91v1fwe","characterId":"f7477cd4-f197-4657-8a90-75b51a39c8b9","_id":116},{"id":1780478324376,"sender":"them","text":"点的什么","timestamp":1780481295969,"tempo":"N","rawContent":"点的什么","roundId":"round_1780481269730_din1nlpik","userId":"uid_1780249711141_mu91v1fwe","characterId":"f7477cd4-f197-4657-8a90-75b51a39c8b9","_id":117},{"id":1780478324377,"sender":"them","text":"尽量吃点热乎的，别光喝冰咖啡","timestamp":1780481297159,"tempo":"N","rawContent":"尽量吃点热乎的，别光喝冰咖啡","roundId":"round_1780481269730_din1nlpik","userId":"uid_1780249711141_mu91v1fwe","characterId":"f7477cd4-f197-4657-8a90-75b51a39c8b9","_id":118},{"id":1780478324378,"sender":"them","text":"晚上回来还有汤，留点肚子","timestamp":1780481299544,"tempo":"S","rawContent":"晚上回来还有汤，留点肚子","roundId":"round_1780481269730_din1nlpik","userId":"uid_1780249711141_mu91v1fwe","characterId":"f7477cd4-f197-4657-8a90-75b51a39c8b9","_id":119},{"id":1780478324379,"text":"好哦","sender":"me","time":"18:08","timestamp":1780481322302,"replyTo":null,"userId":"uid_1780249711141_mu91v1fwe","characterId":"f7477cd4-f197-4657-8a90-75b51a39c8b9","_id":120},{"id":1780478324380,"text":"点的鸡腿饭","sender":"me","time":"18:08","timestamp":1780481331450,"replyTo":null,"userId":"uid_1780249711141_mu91v1fwe","characterId":"f7477cd4-f197-4657-8a90-75b51a39c8b9","_id":121},{"id":1780478324381,"text":"凑合一下","sender":"me","time":"18:08","timestamp":1780481336314,"replyTo":null,"userId":"uid_1780249711141_mu91v1fwe","characterId":"f7477cd4-f197-4657-8a90-75b51a39c8b9","_id":122},{"id":1780478324382,"sender":"them","text":"凑合也比饿着强。","timestamp":1780481349206,"tempo":"N","rawContent":"凑合也比饿着强。","roundId":"round_1780481336990_5ev421pyi","userId":"uid_1780249711141_mu91v1fwe","characterId":"f7477cd4-f197-4657-8a90-75b51a39c8b9","_id":123},{"id":1780478324383,"sender":"them","text":"吃完稍微站一会儿，别马上坐着画图，对胃不好。","timestamp":1780481350913,"tempo":"S","rawContent":"吃完稍微站一会儿，别马上坐着画图，对胃不好。","roundId":"round_1780481336990_5ev421pyi","userId":"uid_1780249711141_mu91v1fwe","characterId":"f7477cd4-f197-4657-8a90-75b51a39c8b9","_id":124},{"id":1780478324384,"sender":"them","text":"晚上见。","timestamp":1780481355991,"tempo":"N","rawContent":"晚上见。","roundId":"round_1780481336990_5ev421pyi","userId":"uid_1780249711141_mu91v1fwe","characterId":"f7477cd4-f197-4657-8a90-75b51a39c8b9","_id":125},{"id":1780478324385,"text":"好晚上见","sender":"me","time":"18:09","timestamp":1780481376314,"replyTo":null,"userId":"uid_1780249711141_mu91v1fwe","characterId":"f7477cd4-f197-4657-8a90-75b51a39c8b9","_id":126},{"id":1780495529052,"text":"下班啦","sender":"me","time":"22:05","timestamp":1780495545020,"replyTo":null,"userId":"uid_1780249711141_mu91v1fwe","characterId":"f7477cd4-f197-4657-8a90-75b51a39c8b9","_id":127},{"id":1780495529053,"sender":"them","text":"十点多了，下班没","timestamp":1780495887832,"tempo":"N","rawContent":"十点多了，下班没","roundId":"round_1780495860383_bkfueeeml","userId":"uid_1780249711141_mu91v1fwe","characterId":"f7477cd4-f197-4657-8a90-75b51a39c8b9","_id":128},{"id":1780495529054,"sender":"them","text":"汤一直温在锅里","timestamp":1780495889319,"tempo":"N","rawContent":"汤一直温在锅里","roundId":"round_1780495860383_bkfueeeml","userId":"uid_1780249711141_mu91v1fwe","characterId":"f7477cd4-f197-4657-8a90-75b51a39c8b9","_id":129},{"id":1780495529055,"sender":"them","text":"汉堡刚才听见走廊有动静，跑去扒了半天门","timestamp":1780495890806,"tempo":"S","rawContent":"汉堡刚才听见走廊有动静，跑去扒了半天门","roundId":"round_1780495860383_bkfueeeml","userId":"uid_1780249711141_mu91v1fwe","characterId":"f7477cd4-f197-4657-8a90-75b51a39c8b9","_id":130},{"id":1780495529056,"text":"正在往家赶了","sender":"me","time":"22:11","timestamp":1780495906686,"replyTo":null,"userId":"uid_1780249711141_mu91v1fwe","characterId":"f7477cd4-f197-4657-8a90-75b51a39c8b9","_id":131},{"id":1780495529057,"text":"有一点点小雨诶","sender":"me","time":"22:11","timestamp":1780495914421,"replyTo":null,"userId":"uid_1780249711141_mu91v1fwe","characterId":"f7477cd4-f197-4657-8a90-75b51a39c8b9","_id":132},{"id":1780495529058,"text":"我要先去拿个快递","sender":"me","time":"22:11","timestamp":1780495919746,"replyTo":null,"userId":"uid_1780249711141_mu91v1fwe","characterId":"f7477cd4-f197-4657-8a90-75b51a39c8b9","_id":133},{"id":1780495529059,"sticker":"https://i.postimg.cc/MpvsLMP5/pic-20260529122820-0.png","text":"表情包：开心","sender":"me","time":"22:12","timestamp":1780495923243,"userId":"uid_1780249711141_mu91v1fwe","characterId":"f7477cd4-f197-4657-8a90-75b51a39c8b9","_id":134},{"id":1780495529060,"text":"期待你的汤hhh","sender":"me","time":"22:12","timestamp":1780495931824,"replyTo":null,"userId":"uid_1780249711141_mu91v1fwe","characterId":"f7477cd4-f197-4657-8a90-75b51a39c8b9","_id":135},{"id":1780495529061,"sender":"them","text":"带伞没","timestamp":1780495953350,"tempo":"R","rawContent":"带伞没","roundId":"round_1780495932593_7o0o710f7","userId":"uid_1780249711141_mu91v1fwe","characterId":"f7477cd4-f197-4657-8a90-75b51a39c8b9","_id":136},{"id":1780495529062,"sender":"them","text":"快递重不重，在小区门口的驿站吗","timestamp":1780495953777,"tempo":"N","rawContent":"快递重不重，在小区门口的驿站吗","roundId":"round_1780495932593_7o0o710f7","userId":"uid_1780249711141_mu91v1fwe","characterId":"f7477cd4-f197-4657-8a90-75b51a39c8b9","_id":137},{"id":1780495529063,"sender":"them","text":"汉堡在屋里憋了一天，我正好带它下楼转转","timestamp":1780495956440,"tempo":"N","rawContent":"汉堡在屋里憋了一天，我正好带它下楼转转","roundId":"round_1780495932593_7o0o710f7","userId":"uid_1780249711141_mu91v1fwe","characterId":"f7477cd4-f197-4657-8a90-75b51a39c8b9","_id":138},{"id":1780495529064,"sender":"them","text":"你在驿站等我，顺手帮你提上来","timestamp":1780495959445,"tempo":"N","rawContent":"你在驿站等我，顺手帮你提上来","roundId":"round_1780495932593_7o0o710f7","userId":"uid_1780249711141_mu91v1fwe","characterId":"f7477cd4-f197-4657-8a90-75b51a39c8b9","_id":139},{"id":1780495529065,"text":"诶没事没事很快的顺路的啦一会就到了","sender":"me","time":"22:13","timestamp":1780495980646,"replyTo":null,"userId":"uid_1780249711141_mu91v1fwe","characterId":"f7477cd4-f197-4657-8a90-75b51a39c8b9","_id":140},{"id":1780495529066,"text":"等我啦","sender":"me","time":"22:13","timestamp":1780495983491,"replyTo":null,"userId":"uid_1780249711141_mu91v1fwe","characterId":"f7477cd4-f197-4657-8a90-75b51a39c8b9","_id":141},{"id":1780495529067,"sticker":"https://i.postimg.cc/GhM7zJQj/pic-20260529122919-0.png","text":"表情包：Thank you","sender":"me","time":"22:13","timestamp":1780495987911,"userId":"uid_1780249711141_mu91v1fwe","characterId":"f7477cd4-f197-4657-8a90-75b51a39c8b9","_id":142},{"id":1780495529068,"text":"真的没事","sender":"me","time":"22:13","timestamp":1780496023675,"replyTo":null,"userId":"uid_1780249711141_mu91v1fwe","characterId":"f7477cd4-f197-4657-8a90-75b51a39c8b9","_id":143},{"id":1780495529069,"text":"等我十分钟哦","sender":"me","time":"22:13","timestamp":1780496026757,"replyTo":null,"userId":"uid_1780249711141_mu91v1fwe","characterId":"f7477cd4-f197-4657-8a90-75b51a39c8b9","_id":144},{"id":1780495529070,"sender":"them","text":"行","timestamp":1780496048640,"tempo":"N","rawContent":"行","roundId":"round_1780496027571_ewnypzj7q","userId":"uid_1780249711141_mu91v1fwe","characterId":"f7477cd4-f197-4657-8a90-75b51a39c8b9","_id":145},{"id":1780495529071,"sender":"them","text":"慢点走，别着急跑","timestamp":1780496049299,"tempo":"S","rawContent":"慢点走，别着急跑","roundId":"round_1780496027571_ewnypzj7q","userId":"uid_1780249711141_mu91v1fwe","characterId":"f7477cd4-f197-4657-8a90-75b51a39c8b9","_id":146},{"id":1780495529072,"sender":"them","text":"汤已经热上了，到了直接敲门","timestamp":1780496052911,"tempo":"N","rawContent":"汤已经热上了，到了直接敲门","roundId":"round_1780496027571_ewnypzj7q","userId":"uid_1780249711141_mu91v1fwe","characterId":"f7477cd4-f197-4657-8a90-75b51a39c8b9","_id":147},{"id":1780575076475,"text":"……","sender":"me","time":"20:31","timestamp":1780576303963,"replyTo":null,"userId":"uid_1780249711141_mu91v1fwe","characterId":"f7477cd4-f197-4657-8a90-75b51a39c8b9","_id":163},{"id":1780575076476,"text":"贺昭驰","sender":"me","time":"20:31","timestamp":1780576315322,"replyTo":null,"userId":"uid_1780249711141_mu91v1fwe","characterId":"f7477cd4-f197-4657-8a90-75b51a39c8b9","_id":164},{"id":1780575076477,"sender":"them","text":"怎么了","timestamp":1780576334826,"tempo":"R","rawContent":"怎么了","roundId":"round_1780576316949_6er5w9563","userId":"uid_1780249711141_mu91v1fwe","characterId":"f7477cd4-f197-4657-8a90-75b51a39c8b9","_id":165},{"id":1780575076478,"sender":"them","text":"在哪","timestamp":1780576335339,"tempo":"R","rawContent":"在哪","roundId":"round_1780576316949_6er5w9563","userId":"uid_1780249711141_mu91v1fwe","characterId":"f7477cd4-f197-4657-8a90-75b51a39c8b9","_id":166},{"id":1780575076479,"sender":"them","text":"发个定位给我，站在原地别动","timestamp":1780576335753,"tempo":"R","rawContent":"发个定位给我，站在原地别动","roundId":"round_1780576316949_6er5w9563","userId":"uid_1780249711141_mu91v1fwe","characterId":"f7477cd4-f197-4657-8a90-75b51a39c8b9","_id":167},{"id":1780575076480,"sender":"them","text":"我马上下去","timestamp":1780576337069,"tempo":"R","rawContent":"我马上下去","roundId":"round_1780576316949_6er5w9563","userId":"uid_1780249711141_mu91v1fwe","characterId":"f7477cd4-f197-4657-8a90-75b51a39c8b9","_id":168},{"id":1780575076481,"text":"我在楼下快递站往回走","sender":"me","time":"20:32","timestamp":1780576360780,"replyTo":null,"userId":"uid_1780249711141_mu91v1fwe","characterId":"f7477cd4-f197-4657-8a90-75b51a39c8b9","_id":169},{"id":1780575076482,"text":"抱歉","sender":"me","time":"20:32","timestamp":1780576365587,"replyTo":null,"userId":"uid_1780249711141_mu91v1fwe","characterId":"f7477cd4-f197-4657-8a90-75b51a39c8b9","_id":170},{"id":1780575076483,"text":"能不能","sender":"me","time":"20:32","timestamp":1780576367275,"replyTo":null,"userId":"uid_1780249711141_mu91v1fwe","characterId":"f7477cd4-f197-4657-8a90-75b51a39c8b9","_id":171},{"id":1780575076484,"text":"下来接一下我","sender":"me","time":"20:32","timestamp":1780576371596,"replyTo":null,"userId":"uid_1780249711141_mu91v1fwe","characterId":"f7477cd4-f197-4657-8a90-75b51a39c8b9","_id":172},{"id":1780575076485,"text":"我有点害怕","sender":"me","time":"20:32","timestamp":1780576375565,"replyTo":null,"userId":"uid_1780249711141_mu91v1fwe","characterId":"f7477cd4-f197-4657-8a90-75b51a39c8b9","_id":173},{"id":1780575076486,"text":"后面好像一直有人跟着我……","sender":"me","time":"20:33","timestamp":1780576384016,"replyTo":null,"userId":"uid_1780249711141_mu91v1fwe","characterId":"f7477cd4-f197-4657-8a90-75b51a39c8b9","_id":174},{"id":1780575076491,"sender":"them","text":"别挂断，也别回头看","timestamp":1780577433246,"tempo":"R","rawContent":"别挂断，也别回头看","roundId":"round_1780577416478_0gmzkslhy","userId":"uid_1780249711141_mu91v1fwe","characterId":"f7477cd4-f197-4657-8a90-75b51a39c8b9","_id":179},{"id":1780575076492,"sender":"them","text":"往人多的地方走，或者找个有光亮、有监控的便利店进去","timestamp":1780577434290,"tempo":"R","rawContent":"往人多的地方走，或者找个有光亮、有监控的便利店进去","roundId":"round_1780577416478_0gmzkslhy","userId":"uid_1780249711141_mu91v1fwe","characterId":"f7477cd4-f197-4657-8a90-75b51a39c8b9","_id":180},{"id":1780575076493,"sender":"them","text":"我马上到，最多两分钟","timestamp":1780577436159,"tempo":"R","rawContent":"我马上到，最多两分钟","roundId":"round_1780577416478_0gmzkslhy","userId":"uid_1780249711141_mu91v1fwe","characterId":"f7477cd4-f197-4657-8a90-75b51a39c8b9","_id":181},{"id":1780575076494,"sender":"them","text":"保持联系，随时告诉我你的位置","timestamp":1780577437292,"tempo":"R","rawContent":"保持联系，随时告诉我你的位置","roundId":"round_1780577416478_0gmzkslhy","userId":"uid_1780249711141_mu91v1fwe","characterId":"f7477cd4-f197-4657-8a90-75b51a39c8b9","_id":182},{"id":1780575076495,"sender":"them","text":"[位置]","timestamp":1780577438746,"tempo":"N","locationData":{"name":"贺昭驰的位置","address":"公寓楼下","distance":"100m"},"rawContent":"[位置]","roundId":"round_1780577416478_0gmzkslhy","userId":"uid_1780249711141_mu91v1fwe","characterId":"f7477cd4-f197-4657-8a90-75b51a39c8b9","_id":183},{"id":1780575076496,"text":"呜","sender":"me","time":"20:52","timestamp":1780577525023,"replyTo":null,"userId":"uid_1780249711141_mu91v1fwe","characterId":"f7477cd4-f197-4657-8a90-75b51a39c8b9","_id":184},{"id":1780575076497,"text":"我感觉越来越近了","sender":"me","time":"20:52","timestamp":1780577535379,"replyTo":null,"userId":"uid_1780249711141_mu91v1fwe","characterId":"f7477cd4-f197-4657-8a90-75b51a39c8b9","_id":185},{"id":1780575076498,"text":"我不敢回头看","sender":"me","time":"20:52","timestamp":1780577539833,"replyTo":null,"userId":"uid_1780249711141_mu91v1fwe","characterId":"f7477cd4-f197-4657-8a90-75b51a39c8b9","_id":186},{"id":1780575076504,"sender":"them","text":"[語音消息]","timestamp":1780577633971,"tempo":"N","isVoice":true,"voice":true,"voiceText":"别怕，小荔，别怕。你听我说，深呼吸。你现在能看到便利店或者保安亭吗？哪怕是人多一点的路口也行。我已经跑出来了，马上就到。你把手机扬声器打开，让他听见我的声音。","minimaxTimbreId":"voice_id_shun","voiceLanguage":"auto","voiceEmotion":"urgent","rawContent":"[語音消息]","roundId":"round_1780577617566_hy037v6lr","audioDuration":17,"userId":"uid_1780249711141_mu91v1fwe","characterId":"f7477cd4-f197-4657-8a90-75b51a39c8b9","_id":192},{"id":1780575076505,"sender":"them","text":"我看到你了","timestamp":1780577634906,"tempo":"R","rawContent":"我看到你了","roundId":"round_1780577617566_hy037v6lr","userId":"uid_1780249711141_mu91v1fwe","characterId":"f7477cd4-f197-4657-8a90-75b51a39c8b9","_id":193},{"id":1780575076506,"sender":"them","text":"站在那别动，我过来了","timestamp":1780577635514,"tempo":"R","rawContent":"站在那别动，我过来了","roundId":"round_1780577617566_hy037v6lr","userId":"uid_1780249711141_mu91v1fwe","characterId":"f7477cd4-f197-4657-8a90-75b51a39c8b9","_id":194},{"id":1780575076507,"text":"好","sender":"me","time":"20:56","timestamp":1780577797433,"replyTo":null,"userId":"uid_1780249711141_mu91v1fwe","characterId":"f7477cd4-f197-4657-8a90-75b51a39c8b9","_id":195},{"id":1780575076508,"text":"我看到你了","sender":"me","time":"20:56","timestamp":1780577801454,"replyTo":null,"userId":"uid_1780249711141_mu91v1fwe","characterId":"f7477cd4-f197-4657-8a90-75b51a39c8b9","_id":196},{"id":1780575076509,"sender":"them","text":"[語音消息]","timestamp":1780577834004,"tempo":"N","isVoice":true,"voice":true,"voiceText":"我在这。别怕，没事了。","minimaxTimbreId":"voice_id_shun","voiceLanguage":"auto","voiceEmotion":"whisper","rawContent":"[語音消息]","roundId":"round_1780577802870_svp700s3w","audioDuration":4,"userId":"uid_1780249711141_mu91v1fwe","characterId":"f7477cd4-f197-4657-8a90-75b51a39c8b9","_id":197},{"id":1780575076510,"sender":"them","type":"offline_invite","text":"","offlineInvite":{"type":"this-moment","scenario":"深夜街头快步将你护在身后"},"timestamp":1780577834907,"roundId":"round_1780577802870_svp700s3w","offlineInviteResponded":"accepted","userId":"uid_1780249711141_mu91v1fwe","characterId":"f7477cd4-f197-4657-8a90-75b51a39c8b9","_id":198},{"id":1780604293958,"sticker":"https://i.postimg.cc/GhM7zJQj/pic-20260529122919-0.png","text":"表情包：Thank you","sender":"me","time":"04:19","timestamp":1780604386956,"userId":"uid_1780249711141_mu91v1fwe","characterId":"f7477cd4-f197-4657-8a90-75b51a39c8b9","_id":199},{"id":1780604293959,"text":"今天在你家","sender":"me","time":"04:24","timestamp":1780604653941,"replyTo":null,"userId":"uid_1780249711141_mu91v1fwe","characterId":"f7477cd4-f197-4657-8a90-75b51a39c8b9","_id":200},{"id":1780604293960,"text":"看到好多头盔和工具","sender":"me","time":"04:24","timestamp":1780604666192,"replyTo":null,"userId":"uid_1780249711141_mu91v1fwe","characterId":"f7477cd4-f197-4657-8a90-75b51a39c8b9","_id":201},{"id":1780604293961,"text":"还有奖杯！","sender":"me","time":"04:24","timestamp":1780604673427,"replyTo":null,"userId":"uid_1780249711141_mu91v1fwe","characterId":"f7477cd4-f197-4657-8a90-75b51a39c8b9","_id":202},{"id":1780604293962,"text":"你平时也好喜欢穿机车外套哦","sender":"me","time":"04:24","timestamp":1780604685052,"replyTo":null,"userId":"uid_1780249711141_mu91v1fwe","characterId":"f7477cd4-f197-4657-8a90-75b51a39c8b9","_id":203},{"id":1780604293963,"sender":"them","text":"嗯，那些算是吃饭的家伙","timestamp":1780604871250,"tempo":"N","rawContent":"嗯，那些算是吃饭的家伙","roundId":"round_1780604831302_eygtvnl16","userId":"uid_1780249711141_mu91v1fwe","characterId":"f7477cd4-f197-4657-8a90-75b51a39c8b9","_id":204},{"id":1780604293964,"sender":"them","text":"机车服防风耐磨，平时穿习惯了","timestamp":1780604873137,"tempo":"N","rawContent":"机车服防风耐磨，平时穿习惯了","roundId":"round_1780604831302_eygtvnl16","userId":"uid_1780249711141_mu91v1fwe","characterId":"f7477cd4-f197-4657-8a90-75b51a39c8b9","_id":205},{"id":1780604293965,"sender":"them","text":"刚才去冲了个冷水澡，没注意手机","timestamp":1780604875636,"tempo":"S","rawContent":"刚才去冲了个冷水澡，没注意手机","roundId":"round_1780604831302_eygtvnl16","userId":"uid_1780249711141_mu91v1fwe","characterId":"f7477cd4-f197-4657-8a90-75b51a39c8b9","_id":206},{"id":1780604293966,"sender":"them","text":"现在快四点半了","timestamp":1780604879957,"tempo":"S","rawContent":"现在快四点半了","roundId":"round_1780604831302_eygtvnl16","userId":"uid_1780249711141_mu91v1fwe","characterId":"f7477cd4-f197-4657-8a90-75b51a39c8b9","_id":207},{"id":1780604293967,"sender":"them","text":"是不是晚上那件事吓到了，一个人睡不着","timestamp":1780604882676,"tempo":"N","rawContent":"是不是晚上那件事吓到了，一个人睡不着","roundId":"round_1780604831302_eygtvnl16","userId":"uid_1780249711141_mu91v1fwe","characterId":"f7477cd4-f197-4657-8a90-75b51a39c8b9","_id":208},{"id":1780604293968,"text":"一点点","sender":"me","time":"04:37","timestamp":1780605422538,"replyTo":null,"userId":"uid_1780249711141_mu91v1fwe","characterId":"f7477cd4-f197-4657-8a90-75b51a39c8b9","_id":209},{"id":1780604293969,"text":"回家看了会视频","sender":"me","time":"04:37","timestamp":1780605428774,"replyTo":null,"userId":"uid_1780249711141_mu91v1fwe","characterId":"f7477cd4-f197-4657-8a90-75b51a39c8b9","_id":210},{"id":1780604293970,"text":"现在安静下来又有点后怕","sender":"me","time":"04:37","timestamp":1780605437562,"replyTo":null,"userId":"uid_1780249711141_mu91v1fwe","characterId":"f7477cd4-f197-4657-8a90-75b51a39c8b9","_id":211},{"id":1780604293971,"text":"还好你来帮我了","sender":"me","time":"04:37","timestamp":1780605442296,"replyTo":null,"rawContent":"还好你来帮我了","isHtml":false,"userId":"uid_1780249711141_mu91v1fwe","characterId":"f7477cd4-f197-4657-8a90-75b51a39c8b9","_id":212},{"id":1780604293972,"sticker":"https://i.postimg.cc/rFhngCJr/pic-20260529122942-0.png","text":"表情包：？","sender":"me","time":"04:37","timestamp":1780605461158,"userId":"uid_1780249711141_mu91v1fwe","characterId":"f7477cd4-f197-4657-8a90-75b51a39c8b9","_id":213},{"id":1780604293973,"text":"你是相关工作的吗","sender":"me","time":"04:37","timestamp":1780605469793,"replyTo":{"id":1780604293963,"text":"嗯，那些算是吃饭的家伙","sender":"them","isSimulated":false},"userId":"uid_1780249711141_mu91v1fwe","characterId":"f7477cd4-f197-4657-8a90-75b51a39c8b9","_id":214},{"id":1780604293985,"sender":"them","text":"算是吧，职业赛车手","timestamp":1780605791978,"tempo":"N","rawContent":"算是吧，职业赛车手","roundId":"round_1780605763197_83m5241bv","userId":"uid_1780249711141_mu91v1fwe","characterId":"f7477cd4-f197-4657-8a90-75b51a39c8b9","_id":226},{"id":1780604293986,"sender":"them","text":"害怕就别一个人硬撑着看视频","timestamp":1780605793728,"tempo":"N","rawContent":"害怕就别一个人硬撑着看视频","roundId":"round_1780605763197_83m5241bv","userId":"uid_1780249711141_mu91v1fwe","characterId":"f7477cd4-f197-4657-8a90-75b51a39c8b9","_id":227},{"id":1780604293987,"sender":"them","text":"我就在你隔壁，一墙之隔","timestamp":1780605795923,"tempo":"S","rawContent":"我就在你隔壁，一墙之隔","roundId":"round_1780605763197_83m5241bv","userId":"uid_1780249711141_mu91v1fwe","characterId":"f7477cd4-f197-4657-8a90-75b51a39c8b9","_id":228},{"id":1780604293988,"sender":"them","text":"要是实在不敢闭眼，打个语音过来把手机放床头，我陪你","timestamp":1780605799619,"tempo":"N","rawContent":"要是实在不敢闭眼，打个语音过来把手机放床头，我陪你","roundId":"round_1780605763197_83m5241bv","userId":"uid_1780249711141_mu91v1fwe","characterId":"f7477cd4-f197-4657-8a90-75b51a39c8b9","_id":229},{"id":1780604293989,"text":"诶好厉害","sender":"me","time":"04:43","timestamp":1780605837549,"replyTo":{"id":1780604293985,"text":"算是吧，职业赛车手","sender":"them","isSimulated":false},"userId":"uid_1780249711141_mu91v1fwe","characterId":"f7477cd4-f197-4657-8a90-75b51a39c8b9","_id":230},{"id":1780604293990,"text":"好少见到的职业","sender":"me","time":"04:44","timestamp":1780605844146,"replyTo":null,"userId":"uid_1780249711141_mu91v1fwe","characterId":"f7477cd4-f197-4657-8a90-75b51a39c8b9","_id":231},{"id":1780604293991,"text":"是拉力还是f1那种呢","sender":"me","time":"04:44","timestamp":1780605851421,"replyTo":null,"userId":"uid_1780249711141_mu91v1fwe","characterId":"f7477cd4-f197-4657-8a90-75b51a39c8b9","_id":232},{"id":1780604293992,"sticker":"https://i.postimg.cc/bws65DCH/pic-20260529122826-0.png","text":"表情包：思考","sender":"me","time":"04:44","timestamp":1780605855380,"userId":"uid_1780249711141_mu91v1fwe","characterId":"f7477cd4-f197-4657-8a90-75b51a39c8b9","_id":233},{"id":1780604293993,"text":"感觉很帅气","sender":"me","time":"04:44","timestamp":1780605859535,"replyTo":null,"userId":"uid_1780249711141_mu91v1fwe","characterId":"f7477cd4-f197-4657-8a90-75b51a39c8b9","_id":234},{"id":1780604293994,"text":"不用啦……太麻烦你了，而且说话很容易精神呢","sender":"me","time":"04:45","timestamp":1780605901419,"replyTo":{"id":1780604293988,"text":"要是实在不敢闭眼，打个语音过来把手机放床头，我陪你","sender":"them","isSimulated":false},"userId":"uid_1780249711141_mu91v1fwe","characterId":"f7477cd4-f197-4657-8a90-75b51a39c8b9","_id":235},{"id":1780604293995,"sender":"them","text":"场地赛，类似F1那种","timestamp":1780605919677,"tempo":"N","rawContent":"场地赛，类似F1那种","roundId":"round_1780605906342_vqbgrgemf","userId":"uid_1780249711141_mu91v1fwe","characterId":"f7477cd4-f197-4657-8a90-75b51a39c8b9","_id":236},{"id":1780604293996,"sender":"them","text":"听起来帅，其实就是个高危体力活","timestamp":1780605921399,"tempo":"S","rawContent":"听起来帅，其实就是个高危体力活","roundId":"round_1780605906342_vqbgrgemf","userId":"uid_1780249711141_mu91v1fwe","characterId":"f7477cd4-f197-4657-8a90-75b51a39c8b9","_id":237},{"id":1780604293997,"sender":"them","text":"那就不说话","timestamp":1780605926088,"tempo":"N","rawContent":"那就不说话","roundId":"round_1780605906342_vqbgrgemf","userId":"uid_1780249711141_mu91v1fwe","characterId":"f7477cd4-f197-4657-8a90-75b51a39c8b9","_id":238},{"id":1780604293998,"sender":"them","text":"你把语音挂着，我这边静音，你听着白噪音睡","timestamp":1780605927416,"tempo":"S","rawContent":"你把语音挂着，我这边静音，你听着白噪音睡","roundId":"round_1780605906342_vqbgrgemf","userId":"uid_1780249711141_mu91v1fwe","characterId":"f7477cd4-f197-4657-8a90-75b51a39c8b9","_id":239},{"id":1780604293999,"sender":"them","text":"或者我去敲门，把汉堡借给你抱一晚？","timestamp":1780605932778,"tempo":"N","rawContent":"或者我去敲门，把汉堡借给你抱一晚？","roundId":"round_1780605906342_vqbgrgemf","userId":"uid_1780249711141_mu91v1fwe","characterId":"f7477cd4-f197-4657-8a90-75b51a39c8b9","_id":240},{"id":1780604294000,"text":"不要欺负汉堡啦","sender":"me","time":"04:46","timestamp":1780605965638,"replyTo":null,"userId":"uid_1780249711141_mu91v1fwe","characterId":"f7477cd4-f197-4657-8a90-75b51a39c8b9","_id":241},{"id":1780604294001,"text":"hhhh","sender":"me","time":"04:46","timestamp":1780605970144,"replyTo":null,"userId":"uid_1780249711141_mu91v1fwe","characterId":"f7477cd4-f197-4657-8a90-75b51a39c8b9","_id":242}]